package com.google.android.gms.analytics.internal;

import android.content.Context;
import android.database.sqlite.SQLiteException;
import android.text.TextUtils;
import android.util.Pair;
import com.google.android.gms.analytics.a;
import com.google.android.gms.analytics.ad;
import com.google.android.gms.analytics.z;
import com.google.android.gms.b.ac;
import com.google.android.gms.b.t;
import com.google.android.gms.common.a.c;
import java.util.ArrayList;
import java.util.HashMap;
import java.util.Iterator;
import java.util.List;
import java.util.Map;
import java.util.Map.Entry;
import java.util.Set;

final class at
  extends af
{
  private boolean a;
  private final aq b;
  private final l c;
  private final k d;
  private final al e;
  private long f;
  private final bj g;
  private final bj h;
  private final s i;
  private long j;
  private boolean k;
  
  protected at(ah paramah, aj paramaj)
  {
    super(paramah);
    com.google.android.gms.common.internal.b.a(paramaj);
    this.f = Long.MIN_VALUE;
    this.d = paramaj.k(paramah);
    this.b = paramaj.m(paramah);
    this.c = paramaj.n(paramah);
    this.e = paramaj.o(paramah);
    this.i = new s(n());
    this.g = new au(this, paramah);
    this.h = new av(this, paramah);
  }
  
  private void J()
  {
    m();
    Context localContext = k().b();
    if (!q.a(localContext)) {
      e("AnalyticsReceiver is not registered or is disabled. Register the receiver for reliable dispatching on non-Google Play devices. See http://goo.gl/8Rd3yj for instructions.");
    }
    do
    {
      while (!a.a(localContext))
      {
        e("CampaignTrackingReceiver is not registered, not exported or is disabled. Installation campaign tracking is not possible. See http://goo.gl/8Rd3yj for instructions.");
        return;
        if (!r.a(localContext)) {
          f("AnalyticsService is not registered or is disabled. Analytics service at risk of not starting. See http://goo.gl/8Rd3yj for instructions.");
        }
      }
    } while (com.google.android.gms.analytics.b.a(localContext));
    e("CampaignTrackingService is not registered or is disabled. Installation campaign tracking is not possible. See http://goo.gl/8Rd3yj for instructions.");
  }
  
  private void K()
  {
    a(new ax(this));
  }
  
  private void L()
  {
    try
    {
      this.b.g();
      G();
      this.h.a(q().C());
      return;
    }
    catch (SQLiteException localSQLiteException)
    {
      for (;;)
      {
        d("Failed to delete stale hits", localSQLiteException);
      }
    }
  }
  
  private boolean M()
  {
    if (this.k) {}
    while (((q().a()) && (!q().b())) || (H() <= 0L)) {
      return false;
    }
    return true;
  }
  
  private void N()
  {
    bm localbm = u();
    if (!localbm.b()) {}
    long l;
    do
    {
      do
      {
        return;
      } while (localbm.c());
      l = F();
    } while ((l == 0L) || (Math.abs(n().a() - l) > q().k()));
    a("Dispatch alarm scheduled (ms)", Long.valueOf(q().j()));
    localbm.d();
  }
  
  private void O()
  {
    N();
    long l2 = H();
    long l1 = w().d();
    if (l1 != 0L)
    {
      l1 = l2 - Math.abs(n().a() - l1);
      if (l1 <= 0L) {}
    }
    for (;;)
    {
      a("Dispatch scheduled (ms)", Long.valueOf(l1));
      if (!this.g.c()) {
        break;
      }
      l1 = Math.max(1L, l1 + this.g.b());
      this.g.b(l1);
      return;
      l1 = Math.min(q().h(), l2);
      continue;
      l1 = Math.min(q().h(), l2);
    }
    this.g.a(l1);
  }
  
  private void P()
  {
    Q();
    R();
  }
  
  private void Q()
  {
    if (this.g.c()) {
      b("All hits dispatched or no network/service. Going to power save mode");
    }
    this.g.d();
  }
  
  private void R()
  {
    bm localbm = u();
    if (localbm.c()) {
      localbm.e();
    }
  }
  
  private void a(ak paramak, com.google.android.gms.b.u paramu)
  {
    com.google.android.gms.common.internal.b.a(paramak);
    com.google.android.gms.common.internal.b.a(paramu);
    Object localObject1 = new com.google.android.gms.analytics.u(k());
    ((com.google.android.gms.analytics.u)localObject1).a(paramak.c());
    ((com.google.android.gms.analytics.u)localObject1).b(paramak.d());
    localObject1 = ((com.google.android.gms.analytics.u)localObject1).l();
    ac localac = (ac)((z)localObject1).b(ac.class);
    localac.a("data");
    localac.b(true);
    ((z)localObject1).a(paramu);
    com.google.android.gms.b.x localx = (com.google.android.gms.b.x)((z)localObject1).b(com.google.android.gms.b.x.class);
    t localt = (t)((z)localObject1).b(t.class);
    Iterator localIterator = paramak.f().entrySet().iterator();
    while (localIterator.hasNext())
    {
      Object localObject2 = (Map.Entry)localIterator.next();
      String str = (String)((Map.Entry)localObject2).getKey();
      localObject2 = (String)((Map.Entry)localObject2).getValue();
      if ("an".equals(str)) {
        localt.a((String)localObject2);
      } else if ("av".equals(str)) {
        localt.b((String)localObject2);
      } else if ("aid".equals(str)) {
        localt.c((String)localObject2);
      } else if ("aiid".equals(str)) {
        localt.d((String)localObject2);
      } else if ("uid".equals(str)) {
        localac.c((String)localObject2);
      } else {
        localx.a(str, (String)localObject2);
      }
    }
    b("Sending installation campaign to", paramak.c(), paramu);
    ((z)localObject1).a(w().b());
    ((z)localObject1).e();
  }
  
  private boolean g(String paramString)
  {
    return o().checkCallingOrSelfPermission(paramString) == 0;
  }
  
  public long F()
  {
    ad.d();
    D();
    try
    {
      long l = this.b.h();
      return l;
    }
    catch (SQLiteException localSQLiteException)
    {
      e("Failed to get min/max hit times from local store", localSQLiteException);
    }
    return 0L;
  }
  
  public void G()
  {
    k().s();
    D();
    if (!M())
    {
      this.d.b();
      P();
      return;
    }
    if (this.b.f())
    {
      this.d.b();
      P();
      return;
    }
    if (!((Boolean)bp.J.a()).booleanValue()) {
      this.d.a();
    }
    for (boolean bool = this.d.e(); bool; bool = true)
    {
      O();
      return;
    }
    P();
    N();
  }
  
  public long H()
  {
    long l;
    if (this.f != Long.MIN_VALUE) {
      l = this.f;
    }
    do
    {
      return l;
      l = q().i();
    } while (!v().f());
    return v().g() * 1000L;
  }
  
  public void I()
  {
    D();
    m();
    this.k = true;
    this.e.d();
    G();
  }
  
  /* Error */
  public long a(ak paramak, boolean paramBoolean)
  {
    // Byte code:
    //   0: aload_1
    //   1: invokestatic 33	com/google/android/gms/common/internal/b:a	(Ljava/lang/Object;)Ljava/lang/Object;
    //   4: pop
    //   5: aload_0
    //   6: invokevirtual 377	com/google/android/gms/analytics/internal/at:D	()V
    //   9: aload_0
    //   10: invokevirtual 88	com/google/android/gms/analytics/internal/at:m	()V
    //   13: aload_0
    //   14: getfield 50	com/google/android/gms/analytics/internal/at:b	Lcom/google/android/gms/analytics/internal/aq;
    //   17: invokevirtual 433	com/google/android/gms/analytics/internal/aq:b	()V
    //   20: aload_0
    //   21: getfield 50	com/google/android/gms/analytics/internal/at:b	Lcom/google/android/gms/analytics/internal/aq;
    //   24: aload_1
    //   25: invokevirtual 434	com/google/android/gms/analytics/internal/ak:a	()J
    //   28: aload_1
    //   29: invokevirtual 436	com/google/android/gms/analytics/internal/ak:b	()Ljava/lang/String;
    //   32: invokevirtual 439	com/google/android/gms/analytics/internal/aq:a	(JLjava/lang/String;)V
    //   35: aload_0
    //   36: getfield 50	com/google/android/gms/analytics/internal/at:b	Lcom/google/android/gms/analytics/internal/aq;
    //   39: aload_1
    //   40: invokevirtual 434	com/google/android/gms/analytics/internal/ak:a	()J
    //   43: aload_1
    //   44: invokevirtual 436	com/google/android/gms/analytics/internal/ak:b	()Ljava/lang/String;
    //   47: aload_1
    //   48: invokevirtual 263	com/google/android/gms/analytics/internal/ak:c	()Ljava/lang/String;
    //   51: invokevirtual 442	com/google/android/gms/analytics/internal/aq:a	(JLjava/lang/String;Ljava/lang/String;)J
    //   54: lstore_3
    //   55: iload_2
    //   56: ifne +32 -> 88
    //   59: aload_1
    //   60: lload_3
    //   61: invokevirtual 443	com/google/android/gms/analytics/internal/ak:a	(J)V
    //   64: aload_0
    //   65: getfield 50	com/google/android/gms/analytics/internal/at:b	Lcom/google/android/gms/analytics/internal/aq;
    //   68: aload_1
    //   69: invokevirtual 446	com/google/android/gms/analytics/internal/aq:a	(Lcom/google/android/gms/analytics/internal/ak;)V
    //   72: aload_0
    //   73: getfield 50	com/google/android/gms/analytics/internal/at:b	Lcom/google/android/gms/analytics/internal/aq;
    //   76: invokevirtual 448	com/google/android/gms/analytics/internal/aq:c	()V
    //   79: aload_0
    //   80: getfield 50	com/google/android/gms/analytics/internal/at:b	Lcom/google/android/gms/analytics/internal/aq;
    //   83: invokevirtual 449	com/google/android/gms/analytics/internal/aq:d	()V
    //   86: lload_3
    //   87: lreturn
    //   88: aload_1
    //   89: lconst_1
    //   90: lload_3
    //   91: ladd
    //   92: invokevirtual 443	com/google/android/gms/analytics/internal/ak:a	(J)V
    //   95: goto -31 -> 64
    //   98: astore_1
    //   99: aload_0
    //   100: ldc_w 451
    //   103: aload_1
    //   104: invokevirtual 382	com/google/android/gms/analytics/internal/at:e	(Ljava/lang/String;Ljava/lang/Object;)V
    //   107: aload_0
    //   108: getfield 50	com/google/android/gms/analytics/internal/at:b	Lcom/google/android/gms/analytics/internal/aq;
    //   111: invokevirtual 449	com/google/android/gms/analytics/internal/aq:d	()V
    //   114: ldc2_w 452
    //   117: lreturn
    //   118: astore_1
    //   119: aload_0
    //   120: ldc_w 455
    //   123: aload_1
    //   124: invokevirtual 382	com/google/android/gms/analytics/internal/at:e	(Ljava/lang/String;Ljava/lang/Object;)V
    //   127: lload_3
    //   128: lreturn
    //   129: astore_1
    //   130: aload_0
    //   131: ldc_w 455
    //   134: aload_1
    //   135: invokevirtual 382	com/google/android/gms/analytics/internal/at:e	(Ljava/lang/String;Ljava/lang/Object;)V
    //   138: goto -24 -> 114
    //   141: astore_1
    //   142: aload_0
    //   143: getfield 50	com/google/android/gms/analytics/internal/at:b	Lcom/google/android/gms/analytics/internal/aq;
    //   146: invokevirtual 449	com/google/android/gms/analytics/internal/aq:d	()V
    //   149: aload_1
    //   150: athrow
    //   151: astore 5
    //   153: aload_0
    //   154: ldc_w 455
    //   157: aload 5
    //   159: invokevirtual 382	com/google/android/gms/analytics/internal/at:e	(Ljava/lang/String;Ljava/lang/Object;)V
    //   162: goto -13 -> 149
    // Local variable table:
    //   start	length	slot	name	signature
    //   0	165	0	this	at
    //   0	165	1	paramak	ak
    //   0	165	2	paramBoolean	boolean
    //   54	74	3	l	long
    //   151	7	5	localSQLiteException	SQLiteException
    // Exception table:
    //   from	to	target	type
    //   13	55	98	android/database/sqlite/SQLiteException
    //   59	64	98	android/database/sqlite/SQLiteException
    //   64	79	98	android/database/sqlite/SQLiteException
    //   88	95	98	android/database/sqlite/SQLiteException
    //   79	86	118	android/database/sqlite/SQLiteException
    //   107	114	129	android/database/sqlite/SQLiteException
    //   13	55	141	finally
    //   59	64	141	finally
    //   64	79	141	finally
    //   88	95	141	finally
    //   99	107	141	finally
    //   142	149	151	android/database/sqlite/SQLiteException
  }
  
  protected void a()
  {
    this.b.E();
    this.c.E();
    this.e.E();
  }
  
  protected void a(ak paramak)
  {
    m();
    b("Sending first hit to property", paramak.c());
    if (w().c().a(q().F())) {}
    do
    {
      return;
      localObject = w().f();
    } while (TextUtils.isEmpty((CharSequence)localObject));
    Object localObject = w.a(p(), (String)localObject);
    b("Found relevant installation campaign", localObject);
    a(paramak, (com.google.android.gms.b.u)localObject);
  }
  
  public void a(bn parambn)
  {
    a(parambn, this.j);
  }
  
  public void a(bn parambn, long paramLong)
  {
    ad.d();
    D();
    long l1 = -1L;
    long l2 = w().d();
    if (l2 != 0L) {
      l1 = Math.abs(n().a() - l2);
    }
    b("Dispatching local hits. Elapsed time since last dispatch (ms)", Long.valueOf(l1));
    if (!q().a()) {
      g();
    }
    try
    {
      if (i())
      {
        r().a(new ay(this, parambn, paramLong));
        return;
      }
      w().e();
      G();
      if (parambn != null) {
        parambn.a(null);
      }
      if (this.j != paramLong)
      {
        this.d.c();
        return;
      }
    }
    catch (Throwable localThrowable)
    {
      e("Local dispatch failed", localThrowable);
      w().e();
      G();
      if (parambn != null) {
        parambn.a(localThrowable);
      }
    }
  }
  
  public void a(d paramd)
  {
    com.google.android.gms.common.internal.b.a(paramd);
    ad.d();
    D();
    if (this.k) {
      c("Hit delivery not possible. Missing network permissions. See http://goo.gl/8Rd3yj for instructions");
    }
    for (;;)
    {
      paramd = b(paramd);
      g();
      if (!this.e.a(paramd)) {
        break;
      }
      c("Hit sent to the device AnalyticsService for delivery");
      return;
      a("Delivering hit", paramd);
    }
    if (q().a())
    {
      p().a(paramd, "Service unavailable on package side");
      return;
    }
    try
    {
      this.b.a(paramd);
      G();
      return;
    }
    catch (SQLiteException localSQLiteException)
    {
      e("Delivery failed to save hit to a database", localSQLiteException);
      p().a(paramd, "deliver: failed to insert hit to database");
    }
  }
  
  public void a(String paramString)
  {
    com.google.android.gms.common.internal.b.a(paramString);
    m();
    l();
    com.google.android.gms.b.u localu = w.a(p(), paramString);
    if (localu == null) {
      d("Parsing failed. Ignoring invalid campaign data", paramString);
    }
    for (;;)
    {
      return;
      String str = w().f();
      if (paramString.equals(str))
      {
        e("Ignoring duplicate install campaign");
        return;
      }
      if (!TextUtils.isEmpty(str))
      {
        d("Ignoring multiple install campaigns. original, new", str, paramString);
        return;
      }
      w().a(paramString);
      if (w().c().a(q().F()))
      {
        d("Campaign received too late, ignoring", localu);
        return;
      }
      b("Received installation campaign", localu);
      paramString = this.b.d(0L).iterator();
      while (paramString.hasNext()) {
        a((ak)paramString.next(), localu);
      }
    }
  }
  
  public void a(boolean paramBoolean)
  {
    G();
  }
  
  d b(d paramd)
  {
    if (!TextUtils.isEmpty(paramd.h())) {}
    do
    {
      return paramd;
      localObject2 = w().g().a();
    } while (localObject2 == null);
    Object localObject1 = (Long)((Pair)localObject2).second;
    Object localObject2 = (String)((Pair)localObject2).first;
    localObject1 = String.valueOf(localObject1);
    localObject1 = String.valueOf(localObject1).length() + 1 + String.valueOf(localObject2).length() + (String)localObject1 + ":" + (String)localObject2;
    localObject2 = new HashMap(paramd.b());
    ((Map)localObject2).put("_m", localObject1);
    return d.a(this, paramd, (Map)localObject2);
  }
  
  void b()
  {
    D();
    if (!this.a) {}
    for (boolean bool = true;; bool = false)
    {
      com.google.android.gms.common.internal.b.a(bool, "Analytics backend already started");
      this.a = true;
      r().a(new aw(this));
      return;
    }
  }
  
  protected void c()
  {
    D();
    if (!q().a()) {
      J();
    }
    w().b();
    if (!g("android.permission.ACCESS_NETWORK_STATE"))
    {
      f("Missing required android.permission.ACCESS_NETWORK_STATE. Google Analytics disabled. See http://goo.gl/8Rd3yj for instructions");
      I();
    }
    if (!g("android.permission.INTERNET"))
    {
      f("Missing required android.permission.INTERNET. Google Analytics disabled. See http://goo.gl/8Rd3yj for instructions");
      I();
    }
    if (r.a(o())) {
      b("AnalyticsService registered in the app manifest and enabled");
    }
    for (;;)
    {
      if ((!this.k) && (!q().a()) && (!this.b.f())) {
        g();
      }
      G();
      return;
      if (q().a()) {
        f("Device AnalyticsService not registered! Hits will not be delivered reliably.");
      } else {
        e("AnalyticsService not registered in the app manifest. Hits might not be delivered reliably. See http://goo.gl/8Rd3yj for instructions.");
      }
    }
  }
  
  void d()
  {
    m();
    this.j = n().a();
  }
  
  protected void e()
  {
    m();
    if (!q().a()) {
      h();
    }
  }
  
  public void f()
  {
    ad.d();
    D();
    b("Service disconnected");
  }
  
  protected void g()
  {
    if (this.k) {}
    do
    {
      long l;
      do
      {
        do
        {
          return;
        } while ((!q().c()) || (this.e.b()));
        l = q().x();
      } while (!this.i.a(l));
      this.i.a();
      b("Connecting to service");
    } while (!this.e.c());
    b("Connected to service");
    this.i.b();
    e();
  }
  
  public void h()
  {
    ad.d();
    D();
    l();
    if (!q().c()) {
      e("Service client disabled. Can't dispatch local hits to device AnalyticsService");
    }
    if (!this.e.b()) {
      b("Service not connected");
    }
    while (this.b.f()) {
      return;
    }
    b("Dispatching local hits to device AnalyticsService");
    for (;;)
    {
      try
      {
        List localList = this.b.b(q().l());
        if (!localList.isEmpty()) {
          break label126;
        }
        G();
        return;
      }
      catch (SQLiteException localSQLiteException1)
      {
        e("Failed to read hits from store", localSQLiteException1);
        P();
        return;
      }
      label107:
      Object localObject;
      localSQLiteException1.remove(localObject);
      try
      {
        this.b.c(((d)localObject).c());
        label126:
        if (!localSQLiteException1.isEmpty())
        {
          localObject = (d)localSQLiteException1.get(0);
          if (this.e.a((d)localObject)) {
            break label107;
          }
          G();
          return;
        }
      }
      catch (SQLiteException localSQLiteException2)
      {
        e("Failed to remove hit that was send for delivery", localSQLiteException2);
        P();
      }
    }
  }
  
  protected boolean i()
  {
    int n = 1;
    ad.d();
    D();
    b("Dispatching a batch of local hits");
    int m;
    if ((!this.e.b()) && (!q().a()))
    {
      m = 1;
      if (this.c.b()) {
        break label70;
      }
    }
    for (;;)
    {
      if ((m == 0) || (n == 0)) {
        break label75;
      }
      b("No network or service available. Will retry later");
      return false;
      m = 0;
      break;
      label70:
      n = 0;
    }
    label75:
    long l3 = Math.max(q().l(), q().m());
    ArrayList localArrayList = new ArrayList();
    l1 = 0L;
    for (;;)
    {
      try
      {
        this.b.b();
        localArrayList.clear();
        try
        {
          localList = this.b.b(l3);
          if (localList.isEmpty())
          {
            b("Store is empty, nothing to dispatch");
            P();
            try
            {
              this.b.c();
              this.b.d();
              return false;
            }
            catch (SQLiteException localSQLiteException1)
            {
              e("Failed to commit local dispatch transaction", localSQLiteException1);
              P();
              return false;
            }
          }
          a("Hits loaded from store. count", Integer.valueOf(localList.size()));
          localObject2 = localList.iterator();
          if (((Iterator)localObject2).hasNext())
          {
            if (((d)((Iterator)localObject2).next()).c() != l1) {
              continue;
            }
            d("Database contains successfully uploaded hit", Long.valueOf(l1), Integer.valueOf(localList.size()));
            P();
            try
            {
              this.b.c();
              this.b.d();
              return false;
            }
            catch (SQLiteException localSQLiteException2)
            {
              e("Failed to commit local dispatch transaction", localSQLiteException2);
              P();
              return false;
            }
          }
          l2 = l1;
        }
        catch (SQLiteException localSQLiteException3)
        {
          d("Failed to read hits from persisted store", localSQLiteException3);
          P();
          try
          {
            this.b.c();
            this.b.d();
            return false;
          }
          catch (SQLiteException localSQLiteException4)
          {
            e("Failed to commit local dispatch transaction", localSQLiteException4);
            P();
            return false;
          }
          l2 = l1;
          if (!this.e.b()) {
            continue;
          }
        }
        if (q().a()) {
          continue;
        }
        b("Service connected, sending hits to the service");
        l2 = l1;
        if (localList.isEmpty()) {
          continue;
        }
        localObject2 = (d)localList.get(0);
        if (this.e.a((d)localObject2)) {
          continue;
        }
      }
      finally
      {
        long l2;
        try
        {
          List localList;
          Object localObject2;
          this.b.c();
          this.b.d();
          throw ((Throwable)localObject1);
        }
        catch (SQLiteException localSQLiteException11)
        {
          e("Failed to commit local dispatch transaction", localSQLiteException11);
          P();
          return false;
        }
        l1 = l2;
        continue;
      }
      l2 = l1;
      if (this.c.b())
      {
        localList = this.c.a(localList);
        localObject2 = localList.iterator();
        if (((Iterator)localObject2).hasNext())
        {
          l1 = Math.max(l1, ((Long)((Iterator)localObject2).next()).longValue());
          continue;
          l1 = Math.max(l1, ((d)localObject2).c());
          localList.remove(localObject2);
          b("Hit sent do device AnalyticsService for delivery", localObject2);
          try
          {
            this.b.c(((d)localObject2).c());
            localSQLiteException4.add(Long.valueOf(((d)localObject2).c()));
          }
          catch (SQLiteException localSQLiteException5)
          {
            e("Failed to remove hit that was send for delivery", localSQLiteException5);
            P();
            try
            {
              this.b.c();
              this.b.d();
              return false;
            }
            catch (SQLiteException localSQLiteException6)
            {
              e("Failed to commit local dispatch transaction", localSQLiteException6);
              P();
              return false;
            }
          }
        }
      }
      try
      {
        this.b.a(localList);
        localSQLiteException6.addAll(localList);
        l2 = l1;
        boolean bool = localSQLiteException6.isEmpty();
        if (bool) {
          try
          {
            this.b.c();
            this.b.d();
            return false;
          }
          catch (SQLiteException localSQLiteException7)
          {
            e("Failed to commit local dispatch transaction", localSQLiteException7);
            P();
            return false;
          }
        }
      }
      catch (SQLiteException localSQLiteException8)
      {
        e("Failed to remove successfully uploaded hits", localSQLiteException8);
        P();
        try
        {
          this.b.c();
          this.b.d();
          return false;
        }
        catch (SQLiteException localSQLiteException9)
        {
          e("Failed to commit local dispatch transaction", localSQLiteException9);
          P();
          return false;
        }
        try
        {
          this.b.c();
          this.b.d();
          l1 = l2;
        }
        catch (SQLiteException localSQLiteException10)
        {
          e("Failed to commit local dispatch transaction", localSQLiteException10);
          P();
          return false;
        }
      }
    }
  }
  
  public void j()
  {
    ad.d();
    D();
    c("Sync dispatching local hits");
    long l = this.j;
    if (!q().a()) {
      g();
    }
    try
    {
      while (i()) {}
      w().e();
      G();
      if (this.j != l) {
        this.d.c();
      }
      return;
    }
    catch (Throwable localThrowable)
    {
      e("Sync local dispatch failed", localThrowable);
      G();
    }
  }
}


/* Location:              D:\Android\dex2jar-2.0\classes-dex2jar.jar!\com\google\android\gms\analytics\internal\at.class
 * Java compiler version: 6 (50.0)
 * JD-Core Version:       0.7.1
 */