package com.sagar.taxiapp.b;

import com.parse.FunctionCallback;

final class aa
  implements FunctionCallback<String>
{
  aa(v paramv, String paramString1, String paramString2) {}
  
  /* Error */
  public void a(String paramString, com.parse.ParseException paramParseException)
  {
    // Byte code:
    //   0: aload_0
    //   1: getfield 16	com/sagar/taxiapp/b/aa:c	Lcom/sagar/taxiapp/b/v;
    //   4: invokestatic 33	com/sagar/taxiapp/b/v:e	(Lcom/sagar/taxiapp/b/v;)Ljava/util/ArrayList;
    //   7: invokevirtual 38	java/util/ArrayList:clear	()V
    //   10: aload_0
    //   11: getfield 16	com/sagar/taxiapp/b/aa:c	Lcom/sagar/taxiapp/b/v;
    //   14: invokestatic 40	com/sagar/taxiapp/b/v:c	(Lcom/sagar/taxiapp/b/v;)Ljava/util/ArrayList;
    //   17: invokevirtual 38	java/util/ArrayList:clear	()V
    //   20: aload_1
    //   21: ifnull +735 -> 756
    //   24: aload_1
    //   25: invokevirtual 46	java/lang/String:isEmpty	()Z
    //   28: ifne +728 -> 756
    //   31: aload_0
    //   32: getfield 16	com/sagar/taxiapp/b/aa:c	Lcom/sagar/taxiapp/b/v;
    //   35: invokestatic 33	com/sagar/taxiapp/b/v:e	(Lcom/sagar/taxiapp/b/v;)Ljava/util/ArrayList;
    //   38: invokevirtual 38	java/util/ArrayList:clear	()V
    //   41: aload_0
    //   42: getfield 16	com/sagar/taxiapp/b/aa:c	Lcom/sagar/taxiapp/b/v;
    //   45: getfield 49	com/sagar/taxiapp/b/v:e	Landroid/support/v4/widget/SwipeRefreshLayout;
    //   48: iconst_0
    //   49: invokevirtual 55	android/support/v4/widget/SwipeRefreshLayout:setRefreshing	(Z)V
    //   52: new 57	org/json/JSONObject
    //   55: dup
    //   56: aload_1
    //   57: invokespecial 60	org/json/JSONObject:<init>	(Ljava/lang/String;)V
    //   60: ldc 62
    //   62: invokevirtual 66	org/json/JSONObject:optJSONArray	(Ljava/lang/String;)Lorg/json/JSONArray;
    //   65: astore_2
    //   66: ldc 68
    //   68: new 70	java/lang/StringBuilder
    //   71: dup
    //   72: invokespecial 71	java/lang/StringBuilder:<init>	()V
    //   75: ldc 73
    //   77: invokevirtual 77	java/lang/StringBuilder:append	(Ljava/lang/String;)Ljava/lang/StringBuilder;
    //   80: aload_1
    //   81: invokevirtual 77	java/lang/StringBuilder:append	(Ljava/lang/String;)Ljava/lang/StringBuilder;
    //   84: invokevirtual 81	java/lang/StringBuilder:toString	()Ljava/lang/String;
    //   87: invokestatic 87	android/util/Log:v	(Ljava/lang/String;Ljava/lang/String;)I
    //   90: pop
    //   91: new 89	org/json/JSONArray
    //   94: dup
    //   95: invokespecial 90	org/json/JSONArray:<init>	()V
    //   98: astore_1
    //   99: new 92	com/parse/ParseGeoPoint
    //   102: dup
    //   103: aload_0
    //   104: getfield 18	com/sagar/taxiapp/b/aa:a	Ljava/lang/String;
    //   107: invokestatic 98	java/lang/Double:parseDouble	(Ljava/lang/String;)D
    //   110: aload_0
    //   111: getfield 20	com/sagar/taxiapp/b/aa:b	Ljava/lang/String;
    //   114: invokestatic 98	java/lang/Double:parseDouble	(Ljava/lang/String;)D
    //   117: invokespecial 101	com/parse/ParseGeoPoint:<init>	(DD)V
    //   120: astore 6
    //   122: aload_0
    //   123: getfield 16	com/sagar/taxiapp/b/aa:c	Lcom/sagar/taxiapp/b/v;
    //   126: new 103	com/parse/ParseObject
    //   129: dup
    //   130: ldc 105
    //   132: invokespecial 106	com/parse/ParseObject:<init>	(Ljava/lang/String;)V
    //   135: putfield 110	com/sagar/taxiapp/b/v:as	Lcom/parse/ParseObject;
    //   138: aload_0
    //   139: getfield 16	com/sagar/taxiapp/b/aa:c	Lcom/sagar/taxiapp/b/v;
    //   142: getfield 110	com/sagar/taxiapp/b/v:as	Lcom/parse/ParseObject;
    //   145: ldc 112
    //   147: aload 6
    //   149: invokevirtual 116	com/parse/ParseObject:put	(Ljava/lang/String;Ljava/lang/Object;)V
    //   152: aload_2
    //   153: ifnull +595 -> 748
    //   156: iconst_0
    //   157: istore_3
    //   158: iload_3
    //   159: aload_2
    //   160: invokevirtual 120	org/json/JSONArray:length	()I
    //   163: if_icmpge +568 -> 731
    //   166: aload_2
    //   167: iload_3
    //   168: invokevirtual 124	org/json/JSONArray:optJSONObject	(I)Lorg/json/JSONObject;
    //   171: astore 8
    //   173: aload 8
    //   175: ifnull +536 -> 711
    //   178: aload 8
    //   180: ldc 126
    //   182: invokevirtual 66	org/json/JSONObject:optJSONArray	(Ljava/lang/String;)Lorg/json/JSONArray;
    //   185: astore 6
    //   187: aload 6
    //   189: invokevirtual 120	org/json/JSONArray:length	()I
    //   192: ifle +519 -> 711
    //   195: aload 8
    //   197: ldc -128
    //   199: invokevirtual 132	org/json/JSONObject:optString	(Ljava/lang/String;)Ljava/lang/String;
    //   202: astore 7
    //   204: aload 8
    //   206: ldc -122
    //   208: invokevirtual 132	org/json/JSONObject:optString	(Ljava/lang/String;)Ljava/lang/String;
    //   211: astore 8
    //   213: iconst_0
    //   214: istore 4
    //   216: iload 4
    //   218: aload 6
    //   220: invokevirtual 120	org/json/JSONArray:length	()I
    //   223: if_icmpge +488 -> 711
    //   226: aload 6
    //   228: iload 4
    //   230: invokevirtual 124	org/json/JSONArray:optJSONObject	(I)Lorg/json/JSONObject;
    //   233: astore 9
    //   235: aload 9
    //   237: ifnull +627 -> 864
    //   240: aload 7
    //   242: invokestatic 139	com/scootapp/tv/d/d:a	(Ljava/lang/String;)I
    //   245: istore 5
    //   247: new 141	com/sagar/taxiapp/beans/h
    //   250: dup
    //   251: invokespecial 142	com/sagar/taxiapp/beans/h:<init>	()V
    //   254: astore 10
    //   256: aload 10
    //   258: aload 9
    //   260: ldc -112
    //   262: invokevirtual 132	org/json/JSONObject:optString	(Ljava/lang/String;)Ljava/lang/String;
    //   265: invokestatic 147	com/scootapp/tv/d/e:a	(Ljava/lang/String;)I
    //   268: putfield 150	com/sagar/taxiapp/beans/h:b	I
    //   271: aload 10
    //   273: aload 9
    //   275: ldc -104
    //   277: invokevirtual 132	org/json/JSONObject:optString	(Ljava/lang/String;)Ljava/lang/String;
    //   280: putfield 154	com/sagar/taxiapp/beans/h:c	Ljava/lang/String;
    //   283: aload 10
    //   285: iload 5
    //   287: putfield 157	com/sagar/taxiapp/beans/h:d	I
    //   290: aload 9
    //   292: ldc -97
    //   294: invokevirtual 132	org/json/JSONObject:optString	(Ljava/lang/String;)Ljava/lang/String;
    //   297: astore 11
    //   299: aload 11
    //   301: invokevirtual 46	java/lang/String:isEmpty	()Z
    //   304: ifeq +237 -> 541
    //   307: aload 10
    //   309: ldc -95
    //   311: putfield 164	com/sagar/taxiapp/beans/h:g	Ljava/lang/String;
    //   314: aload 10
    //   316: aload 9
    //   318: ldc -90
    //   320: invokevirtual 132	org/json/JSONObject:optString	(Ljava/lang/String;)Ljava/lang/String;
    //   323: putfield 169	com/sagar/taxiapp/beans/h:h	Ljava/lang/String;
    //   326: aload 10
    //   328: getfield 169	com/sagar/taxiapp/beans/h:h	Ljava/lang/String;
    //   331: invokevirtual 46	java/lang/String:isEmpty	()Z
    //   334: ifeq +10 -> 344
    //   337: aload 10
    //   339: ldc -85
    //   341: putfield 169	com/sagar/taxiapp/beans/h:h	Ljava/lang/String;
    //   344: aload 10
    //   346: aload 9
    //   348: ldc -83
    //   350: invokevirtual 132	org/json/JSONObject:optString	(Ljava/lang/String;)Ljava/lang/String;
    //   353: putfield 174	com/sagar/taxiapp/beans/h:a	Ljava/lang/String;
    //   356: aload 10
    //   358: aload 9
    //   360: ldc -80
    //   362: invokevirtual 132	org/json/JSONObject:optString	(Ljava/lang/String;)Ljava/lang/String;
    //   365: putfield 179	com/sagar/taxiapp/beans/h:i	Ljava/lang/String;
    //   368: aload 10
    //   370: aload 9
    //   372: ldc -75
    //   374: invokevirtual 184	org/json/JSONObject:optDouble	(Ljava/lang/String;)D
    //   377: putfield 188	com/sagar/taxiapp/beans/h:j	D
    //   380: aload 10
    //   382: getfield 188	com/sagar/taxiapp/beans/h:j	D
    //   385: invokestatic 192	java/lang/Double:isNaN	(D)Z
    //   388: ifeq +9 -> 397
    //   391: aload 10
    //   393: dconst_0
    //   394: putfield 188	com/sagar/taxiapp/beans/h:j	D
    //   397: aload 10
    //   399: aload 7
    //   401: putfield 195	com/sagar/taxiapp/beans/h:f	Ljava/lang/String;
    //   404: aload 10
    //   406: aload 8
    //   408: putfield 197	com/sagar/taxiapp/beans/h:e	Ljava/lang/String;
    //   411: aload_0
    //   412: getfield 16	com/sagar/taxiapp/b/aa:c	Lcom/sagar/taxiapp/b/v;
    //   415: getfield 201	com/sagar/taxiapp/b/v:ak	Landroid/content/SharedPreferences;
    //   418: ldc -53
    //   420: iconst_0
    //   421: invokeinterface 209 3 0
    //   426: ifne +151 -> 577
    //   429: aload_1
    //   430: new 70	java/lang/StringBuilder
    //   433: dup
    //   434: invokespecial 71	java/lang/StringBuilder:<init>	()V
    //   437: aload 10
    //   439: getfield 195	com/sagar/taxiapp/beans/h:f	Ljava/lang/String;
    //   442: invokevirtual 77	java/lang/StringBuilder:append	(Ljava/lang/String;)Ljava/lang/StringBuilder;
    //   445: ldc -45
    //   447: invokevirtual 77	java/lang/StringBuilder:append	(Ljava/lang/String;)Ljava/lang/StringBuilder;
    //   450: aload 10
    //   452: getfield 150	com/sagar/taxiapp/beans/h:b	I
    //   455: invokevirtual 214	java/lang/StringBuilder:append	(I)Ljava/lang/StringBuilder;
    //   458: ldc -45
    //   460: invokevirtual 77	java/lang/StringBuilder:append	(Ljava/lang/String;)Ljava/lang/StringBuilder;
    //   463: aload 10
    //   465: getfield 154	com/sagar/taxiapp/beans/h:c	Ljava/lang/String;
    //   468: invokevirtual 77	java/lang/StringBuilder:append	(Ljava/lang/String;)Ljava/lang/StringBuilder;
    //   471: ldc -45
    //   473: invokevirtual 77	java/lang/StringBuilder:append	(Ljava/lang/String;)Ljava/lang/StringBuilder;
    //   476: aload 10
    //   478: getfield 164	com/sagar/taxiapp/beans/h:g	Ljava/lang/String;
    //   481: invokevirtual 77	java/lang/StringBuilder:append	(Ljava/lang/String;)Ljava/lang/StringBuilder;
    //   484: aload 10
    //   486: getfield 174	com/sagar/taxiapp/beans/h:a	Ljava/lang/String;
    //   489: invokevirtual 77	java/lang/StringBuilder:append	(Ljava/lang/String;)Ljava/lang/StringBuilder;
    //   492: ldc -40
    //   494: invokevirtual 77	java/lang/StringBuilder:append	(Ljava/lang/String;)Ljava/lang/StringBuilder;
    //   497: aload 10
    //   499: getfield 169	com/sagar/taxiapp/beans/h:h	Ljava/lang/String;
    //   502: invokevirtual 77	java/lang/StringBuilder:append	(Ljava/lang/String;)Ljava/lang/StringBuilder;
    //   505: ldc -45
    //   507: invokevirtual 77	java/lang/StringBuilder:append	(Ljava/lang/String;)Ljava/lang/StringBuilder;
    //   510: aload 10
    //   512: getfield 188	com/sagar/taxiapp/beans/h:j	D
    //   515: invokevirtual 219	java/lang/StringBuilder:append	(D)Ljava/lang/StringBuilder;
    //   518: invokevirtual 81	java/lang/StringBuilder:toString	()Ljava/lang/String;
    //   521: invokevirtual 222	org/json/JSONArray:put	(Ljava/lang/Object;)Lorg/json/JSONArray;
    //   524: pop
    //   525: aload_0
    //   526: getfield 16	com/sagar/taxiapp/b/aa:c	Lcom/sagar/taxiapp/b/v;
    //   529: invokestatic 33	com/sagar/taxiapp/b/v:e	(Lcom/sagar/taxiapp/b/v;)Ljava/util/ArrayList;
    //   532: aload 10
    //   534: invokevirtual 226	java/util/ArrayList:add	(Ljava/lang/Object;)Z
    //   537: pop
    //   538: goto +326 -> 864
    //   541: aload 11
    //   543: ldc -28
    //   545: invokevirtual 232	java/lang/String:equalsIgnoreCase	(Ljava/lang/String;)Z
    //   548: ifeq +19 -> 567
    //   551: aload 10
    //   553: ldc -95
    //   555: putfield 164	com/sagar/taxiapp/beans/h:g	Ljava/lang/String;
    //   558: goto -244 -> 314
    //   561: astore_1
    //   562: aload_1
    //   563: invokevirtual 235	java/lang/Exception:printStackTrace	()V
    //   566: return
    //   567: aload 10
    //   569: aload 11
    //   571: putfield 164	com/sagar/taxiapp/beans/h:g	Ljava/lang/String;
    //   574: goto -260 -> 314
    //   577: aload_0
    //   578: getfield 16	com/sagar/taxiapp/b/aa:c	Lcom/sagar/taxiapp/b/v;
    //   581: getfield 201	com/sagar/taxiapp/b/v:ak	Landroid/content/SharedPreferences;
    //   584: ldc -53
    //   586: iconst_0
    //   587: invokeinterface 209 3 0
    //   592: ifeq -67 -> 525
    //   595: aload_1
    //   596: new 70	java/lang/StringBuilder
    //   599: dup
    //   600: invokespecial 71	java/lang/StringBuilder:<init>	()V
    //   603: aload 10
    //   605: getfield 195	com/sagar/taxiapp/beans/h:f	Ljava/lang/String;
    //   608: invokevirtual 77	java/lang/StringBuilder:append	(Ljava/lang/String;)Ljava/lang/StringBuilder;
    //   611: ldc -45
    //   613: invokevirtual 77	java/lang/StringBuilder:append	(Ljava/lang/String;)Ljava/lang/StringBuilder;
    //   616: aload 10
    //   618: getfield 150	com/sagar/taxiapp/beans/h:b	I
    //   621: invokevirtual 214	java/lang/StringBuilder:append	(I)Ljava/lang/StringBuilder;
    //   624: ldc -45
    //   626: invokevirtual 77	java/lang/StringBuilder:append	(Ljava/lang/String;)Ljava/lang/StringBuilder;
    //   629: aload 10
    //   631: getfield 154	com/sagar/taxiapp/beans/h:c	Ljava/lang/String;
    //   634: invokevirtual 77	java/lang/StringBuilder:append	(Ljava/lang/String;)Ljava/lang/StringBuilder;
    //   637: ldc -45
    //   639: invokevirtual 77	java/lang/StringBuilder:append	(Ljava/lang/String;)Ljava/lang/StringBuilder;
    //   642: aload 10
    //   644: getfield 174	com/sagar/taxiapp/beans/h:a	Ljava/lang/String;
    //   647: invokevirtual 77	java/lang/StringBuilder:append	(Ljava/lang/String;)Ljava/lang/StringBuilder;
    //   650: invokevirtual 81	java/lang/StringBuilder:toString	()Ljava/lang/String;
    //   653: invokevirtual 222	org/json/JSONArray:put	(Ljava/lang/Object;)Lorg/json/JSONArray;
    //   656: pop
    //   657: aload 10
    //   659: getfield 174	com/sagar/taxiapp/beans/h:a	Ljava/lang/String;
    //   662: ldc -19
    //   664: invokevirtual 232	java/lang/String:equalsIgnoreCase	(Ljava/lang/String;)Z
    //   667: ifne -142 -> 525
    //   670: aload 10
    //   672: getfield 174	com/sagar/taxiapp/beans/h:a	Ljava/lang/String;
    //   675: ldc -17
    //   677: invokevirtual 232	java/lang/String:equalsIgnoreCase	(Ljava/lang/String;)Z
    //   680: ifne -155 -> 525
    //   683: aload 10
    //   685: getfield 174	com/sagar/taxiapp/beans/h:a	Ljava/lang/String;
    //   688: ldc -15
    //   690: invokevirtual 232	java/lang/String:equalsIgnoreCase	(Ljava/lang/String;)Z
    //   693: ifne -168 -> 525
    //   696: aload_0
    //   697: getfield 16	com/sagar/taxiapp/b/aa:c	Lcom/sagar/taxiapp/b/v;
    //   700: aload 10
    //   702: getfield 174	com/sagar/taxiapp/beans/h:a	Ljava/lang/String;
    //   705: invokestatic 244	com/sagar/taxiapp/b/v:b	(Lcom/sagar/taxiapp/b/v;Ljava/lang/String;)V
    //   708: goto -183 -> 525
    //   711: aload_0
    //   712: getfield 16	com/sagar/taxiapp/b/aa:c	Lcom/sagar/taxiapp/b/v;
    //   715: getfield 110	com/sagar/taxiapp/b/v:as	Lcom/parse/ParseObject;
    //   718: ldc -10
    //   720: aload_1
    //   721: invokevirtual 116	com/parse/ParseObject:put	(Ljava/lang/String;Ljava/lang/Object;)V
    //   724: iload_3
    //   725: iconst_1
    //   726: iadd
    //   727: istore_3
    //   728: goto -570 -> 158
    //   731: aload_0
    //   732: getfield 16	com/sagar/taxiapp/b/aa:c	Lcom/sagar/taxiapp/b/v;
    //   735: invokestatic 249	com/sagar/taxiapp/b/v:f	(Lcom/sagar/taxiapp/b/v;)Lcom/sagar/taxiapp/a/q;
    //   738: aload_0
    //   739: getfield 16	com/sagar/taxiapp/b/aa:c	Lcom/sagar/taxiapp/b/v;
    //   742: invokestatic 33	com/sagar/taxiapp/b/v:e	(Lcom/sagar/taxiapp/b/v;)Ljava/util/ArrayList;
    //   745: invokevirtual 254	com/sagar/taxiapp/a/q:a	(Ljava/util/ArrayList;)V
    //   748: aload_0
    //   749: getfield 16	com/sagar/taxiapp/b/aa:c	Lcom/sagar/taxiapp/b/v;
    //   752: invokestatic 258	com/sagar/taxiapp/b/v:B	(Lcom/sagar/taxiapp/b/v;)V
    //   755: return
    //   756: aload_2
    //   757: ifnonnull +7 -> 764
    //   760: aload_1
    //   761: ifnonnull -195 -> 566
    //   764: ldc 68
    //   766: new 70	java/lang/StringBuilder
    //   769: dup
    //   770: invokespecial 71	java/lang/StringBuilder:<init>	()V
    //   773: ldc 73
    //   775: invokevirtual 77	java/lang/StringBuilder:append	(Ljava/lang/String;)Ljava/lang/StringBuilder;
    //   778: aload_1
    //   779: invokevirtual 77	java/lang/StringBuilder:append	(Ljava/lang/String;)Ljava/lang/StringBuilder;
    //   782: invokevirtual 81	java/lang/StringBuilder:toString	()Ljava/lang/String;
    //   785: invokestatic 87	android/util/Log:v	(Ljava/lang/String;Ljava/lang/String;)I
    //   788: pop
    //   789: aload_0
    //   790: getfield 16	com/sagar/taxiapp/b/aa:c	Lcom/sagar/taxiapp/b/v;
    //   793: getfield 261	com/sagar/taxiapp/b/v:au	I
    //   796: iconst_3
    //   797: if_icmpge +40 -> 837
    //   800: aload_0
    //   801: getfield 16	com/sagar/taxiapp/b/aa:c	Lcom/sagar/taxiapp/b/v;
    //   804: ldc_w 263
    //   807: invokevirtual 265	com/sagar/taxiapp/b/v:b	(Ljava/lang/String;)V
    //   810: aload_0
    //   811: getfield 16	com/sagar/taxiapp/b/aa:c	Lcom/sagar/taxiapp/b/v;
    //   814: getfield 49	com/sagar/taxiapp/b/v:e	Landroid/support/v4/widget/SwipeRefreshLayout;
    //   817: iconst_1
    //   818: invokevirtual 55	android/support/v4/widget/SwipeRefreshLayout:setRefreshing	(Z)V
    //   821: aload_0
    //   822: getfield 16	com/sagar/taxiapp/b/aa:c	Lcom/sagar/taxiapp/b/v;
    //   825: aload_0
    //   826: getfield 18	com/sagar/taxiapp/b/aa:a	Ljava/lang/String;
    //   829: aload_0
    //   830: getfield 20	com/sagar/taxiapp/b/aa:b	Ljava/lang/String;
    //   833: invokestatic 267	com/sagar/taxiapp/b/v:b	(Lcom/sagar/taxiapp/b/v;Ljava/lang/String;Ljava/lang/String;)V
    //   836: return
    //   837: aload_0
    //   838: getfield 16	com/sagar/taxiapp/b/aa:c	Lcom/sagar/taxiapp/b/v;
    //   841: ldc_w 269
    //   844: invokevirtual 265	com/sagar/taxiapp/b/v:b	(Ljava/lang/String;)V
    //   847: aload_0
    //   848: getfield 16	com/sagar/taxiapp/b/aa:c	Lcom/sagar/taxiapp/b/v;
    //   851: getfield 49	com/sagar/taxiapp/b/v:e	Landroid/support/v4/widget/SwipeRefreshLayout;
    //   854: iconst_0
    //   855: invokevirtual 55	android/support/v4/widget/SwipeRefreshLayout:setRefreshing	(Z)V
    //   858: return
    //   859: astore 6
    //   861: goto -709 -> 152
    //   864: iload 4
    //   866: iconst_1
    //   867: iadd
    //   868: istore 4
    //   870: goto -654 -> 216
    // Local variable table:
    //   start	length	slot	name	signature
    //   0	873	0	this	aa
    //   0	873	1	paramString	String
    //   0	873	2	paramParseException	com.parse.ParseException
    //   157	571	3	i	int
    //   214	655	4	j	int
    //   245	41	5	k	int
    //   120	107	6	localObject1	Object
    //   859	1	6	localException	Exception
    //   202	198	7	str1	String
    //   171	236	8	localObject2	Object
    //   233	138	9	localJSONObject	org.json.JSONObject
    //   254	447	10	localh	com.sagar.taxiapp.beans.h
    //   297	273	11	str2	String
    // Exception table:
    //   from	to	target	type
    //   31	99	561	java/lang/Exception
    //   158	173	561	java/lang/Exception
    //   178	213	561	java/lang/Exception
    //   216	235	561	java/lang/Exception
    //   240	314	561	java/lang/Exception
    //   314	344	561	java/lang/Exception
    //   344	397	561	java/lang/Exception
    //   397	525	561	java/lang/Exception
    //   525	538	561	java/lang/Exception
    //   541	558	561	java/lang/Exception
    //   567	574	561	java/lang/Exception
    //   577	708	561	java/lang/Exception
    //   711	724	561	java/lang/Exception
    //   731	748	561	java/lang/Exception
    //   748	755	561	java/lang/Exception
    //   99	152	859	java/lang/Exception
  }
}


/* Location:              D:\Android\dex2jar-2.0\classes-dex2jar.jar!\com\sagar\taxiapp\b\aa.class
 * Java compiler version: 6 (50.0)
 * JD-Core Version:       0.7.1
 */