package com.appsee;

import android.os.Handler;
import android.os.Looper;

class cf
  extends Handler
{
  cf(nn paramnn, Looper paramLooper)
  {
    super(paramLooper);
  }
  
  /* Error */
  public void handleMessage(android.os.Message arg1)
  {
    // Byte code:
    //   0: aload_1
    //   1: getfield 24	android/os/Message:what	I
    //   4: tableswitch	default:+20->24, 1:+21->25
    //   24: return
    //   25: aload_0
    //   26: getfield 10	com/appsee/cf:l	Lcom/appsee/nn;
    //   29: getfield 30	com/appsee/nn:f	Lcom/appsee/xn;
    //   32: invokestatic 36	com/appsee/xn:C	(Lcom/appsee/xn;)V
    //   35: aload_0
    //   36: getfield 10	com/appsee/cf:l	Lcom/appsee/nn;
    //   39: invokestatic 39	com/appsee/nn:C	(Lcom/appsee/nn;)Ljava/lang/Object;
    //   42: astore_1
    //   43: aload_1
    //   44: monitorenter
    //   45: aload_0
    //   46: getfield 10	com/appsee/cf:l	Lcom/appsee/nn;
    //   49: invokestatic 39	com/appsee/nn:C	(Lcom/appsee/nn;)Ljava/lang/Object;
    //   52: invokevirtual 45	java/lang/Object:notify	()V
    //   55: aload_1
    //   56: monitorexit
    //   57: return
    //   58: astore_2
    //   59: aload_1
    //   60: monitorexit
    //   61: aload_2
    //   62: athrow
    //   63: astore_1
    //   64: aload_0
    //   65: getfield 10	com/appsee/cf:l	Lcom/appsee/nn;
    //   68: aload_1
    //   69: invokestatic 48	com/appsee/nn:C	(Lcom/appsee/nn;Ljava/lang/Exception;)Ljava/lang/Exception;
    //   72: pop
    //   73: aload_0
    //   74: getfield 10	com/appsee/cf:l	Lcom/appsee/nn;
    //   77: invokestatic 39	com/appsee/nn:C	(Lcom/appsee/nn;)Ljava/lang/Object;
    //   80: astore_1
    //   81: aload_1
    //   82: monitorenter
    //   83: aload_0
    //   84: getfield 10	com/appsee/cf:l	Lcom/appsee/nn;
    //   87: invokestatic 39	com/appsee/nn:C	(Lcom/appsee/nn;)Ljava/lang/Object;
    //   90: invokevirtual 45	java/lang/Object:notify	()V
    //   93: aload_1
    //   94: monitorexit
    //   95: return
    //   96: astore_2
    //   97: aload_1
    //   98: monitorexit
    //   99: aload_2
    //   100: athrow
    //   101: astore_2
    //   102: aload_0
    //   103: getfield 10	com/appsee/cf:l	Lcom/appsee/nn;
    //   106: invokestatic 39	com/appsee/nn:C	(Lcom/appsee/nn;)Ljava/lang/Object;
    //   109: astore_1
    //   110: aload_1
    //   111: monitorenter
    //   112: aload_0
    //   113: getfield 10	com/appsee/cf:l	Lcom/appsee/nn;
    //   116: invokestatic 39	com/appsee/nn:C	(Lcom/appsee/nn;)Ljava/lang/Object;
    //   119: invokevirtual 45	java/lang/Object:notify	()V
    //   122: aload_1
    //   123: monitorexit
    //   124: aload_2
    //   125: athrow
    //   126: astore_2
    //   127: aload_1
    //   128: monitorexit
    //   129: aload_2
    //   130: athrow
    // Local variable table:
    //   start	length	slot	name	signature
    //   0	131	0	this	cf
    //   58	4	2	localObject1	Object
    //   96	4	2	localObject2	Object
    //   101	24	2	localObject3	Object
    //   126	4	2	localObject4	Object
    // Exception table:
    //   from	to	target	type
    //   45	57	58	finally
    //   59	61	58	finally
    //   25	35	63	java/lang/Exception
    //   83	95	96	finally
    //   97	99	96	finally
    //   25	35	101	finally
    //   64	73	101	finally
    //   112	124	126	finally
    //   127	129	126	finally
  }
}


/* Location:              D:\Android\dex2jar-2.0\classes-dex2jar.jar!\com\appsee\cf.class
 * Java compiler version: 6 (50.0)
 * JD-Core Version:       0.7.1
 */