package com.appsee;

import java.util.ArrayList;
import java.util.List;

class pd
{
  private int A;
  private final List<bd> B = new ArrayList();
  private boolean D = false;
  private int G;
  private final List<bd> M = new ArrayList();
  private int l;
  
  public pd(int paramInt1, int paramInt2, int paramInt3)
  {
    C(paramInt1, paramInt2, paramInt3);
  }
  
  public bd C()
  {
    bd localbd1 = null;
    for (;;)
    {
      try
      {
        if (this.D)
        {
          vd.H(2, bc.C(" .\r5\032;T(\033|\0239\000|\025|\0270\021=\0329\020|\026)\022:\021."));
          return localbd1;
        }
        if (this.M.isEmpty()) {
          vd.H(2, sc.C("G\r)\013d\003n\007)\000|\004o\007{Bh\024h\013e\003k\016lBo\r{B\013m\007fB{\007g\006l\020`\fnN)\021b\013y\022`\fnBo\020h\017lL'L"));
        } else {
          bd localbd2 = (bd)this.M.remove(0);
        }
      }
      finally {}
    }
  }
  
  public void C()
  {
    try
    {
      if ((this.G != this.M.size()) && (!this.D)) {
        vd.H(1, sc.C("+d\003n\007)\000|\004o\007{By\rf\016)\006f\007z\f.\026)\nh\024lBh\016eBh\016e\rj\003}\007mBk\027o\004l\020zBo\r{Bj\016l\003g\013g\005"));
      }
      this.M.clear();
      this.D = true;
      return;
    }
    finally {}
  }
  
  /* Error */
  public void C(bd parambd)
  {
    // Byte code:
    //   0: aload_0
    //   1: monitorenter
    //   2: aload_1
    //   3: ifnull +12 -> 15
    //   6: aload_0
    //   7: getfield 28	com/appsee/pd:D	Z
    //   10: istore_2
    //   11: iload_2
    //   12: ifeq +6 -> 18
    //   15: aload_0
    //   16: monitorexit
    //   17: return
    //   18: aload_1
    //   19: invokevirtual 99	com/appsee/bd:C	()Landroid/graphics/Canvas;
    //   22: ldc 100
    //   24: invokevirtual 106	android/graphics/Canvas:drawColor	(I)V
    //   27: aload_1
    //   28: invokevirtual 107	com/appsee/bd:C	()V
    //   31: aload_0
    //   32: getfield 24	com/appsee/pd:M	Ljava/util/List;
    //   35: aload_1
    //   36: invokeinterface 110 2 0
    //   41: ifne -26 -> 15
    //   44: aload_0
    //   45: getfield 24	com/appsee/pd:M	Ljava/util/List;
    //   48: aload_1
    //   49: invokeinterface 43 2 0
    //   54: pop
    //   55: goto -40 -> 15
    //   58: astore_1
    //   59: aload_0
    //   60: monitorexit
    //   61: aload_1
    //   62: athrow
    // Local variable table:
    //   start	length	slot	name	signature
    //   0	63	0	this	pd
    //   0	63	1	parambd	bd
    //   10	2	2	bool	boolean
    // Exception table:
    //   from	to	target	type
    //   6	11	58	finally
    //   18	55	58	finally
  }
  
  /* Error */
  public void H(int paramInt1, int paramInt2, int paramInt3)
  {
    // Byte code:
    //   0: iconst_0
    //   1: istore 4
    //   3: aload_0
    //   4: monitorenter
    //   5: iload_2
    //   6: aload_0
    //   7: getfield 47	com/appsee/pd:l	I
    //   10: if_icmpne +11 -> 21
    //   13: iload_3
    //   14: aload_0
    //   15: getfield 49	com/appsee/pd:A	I
    //   18: if_icmpeq +26 -> 44
    //   21: iconst_1
    //   22: ldc 112
    //   24: invokestatic 76	com/appsee/bc:C	(Ljava/lang/String;)Ljava/lang/String;
    //   27: invokestatic 81	com/appsee/vd:H	(ILjava/lang/String;)V
    //   30: aload_0
    //   31: invokespecial 114	com/appsee/pd:H	()V
    //   34: aload_0
    //   35: iload_1
    //   36: iload_2
    //   37: iload_3
    //   38: invokespecial 31	com/appsee/pd:C	(III)V
    //   41: aload_0
    //   42: monitorexit
    //   43: return
    //   44: aload_0
    //   45: getfield 24	com/appsee/pd:M	Ljava/util/List;
    //   48: invokeinterface 68 1 0
    //   53: aload_0
    //   54: iconst_0
    //   55: putfield 28	com/appsee/pd:D	Z
    //   58: aload_0
    //   59: getfield 24	com/appsee/pd:M	Ljava/util/List;
    //   62: aload_0
    //   63: getfield 26	com/appsee/pd:B	Ljava/util/List;
    //   66: invokeinterface 118 2 0
    //   71: pop
    //   72: iload_1
    //   73: aload_0
    //   74: getfield 45	com/appsee/pd:G	I
    //   77: if_icmpeq -36 -> 41
    //   80: iload_1
    //   81: aload_0
    //   82: getfield 45	com/appsee/pd:G	I
    //   85: if_icmple +65 -> 150
    //   88: iload_1
    //   89: aload_0
    //   90: getfield 45	com/appsee/pd:G	I
    //   93: isub
    //   94: istore_3
    //   95: iconst_1
    //   96: ldc 120
    //   98: invokestatic 90	com/appsee/sc:C	(Ljava/lang/String;)Ljava/lang/String;
    //   101: iconst_1
    //   102: anewarray 4	java/lang/Object
    //   105: dup
    //   106: iconst_0
    //   107: iload_3
    //   108: invokestatic 126	java/lang/Integer:valueOf	(I)Ljava/lang/Integer;
    //   111: aastore
    //   112: invokestatic 129	com/appsee/vd:C	(ILjava/lang/String;[Ljava/lang/Object;)V
    //   115: iconst_0
    //   116: istore_1
    //   117: iload 4
    //   119: istore_2
    //   120: iload_2
    //   121: iload_3
    //   122: if_icmpge -81 -> 41
    //   125: aload_0
    //   126: getfield 47	com/appsee/pd:l	I
    //   129: istore 4
    //   131: iload_1
    //   132: iconst_1
    //   133: iadd
    //   134: istore_2
    //   135: aload_0
    //   136: iload 4
    //   138: aload_0
    //   139: getfield 49	com/appsee/pd:A	I
    //   142: invokespecial 51	com/appsee/pd:C	(II)V
    //   145: iload_2
    //   146: istore_1
    //   147: goto -27 -> 120
    //   150: aload_0
    //   151: getfield 45	com/appsee/pd:G	I
    //   154: iload_1
    //   155: isub
    //   156: istore_2
    //   157: iconst_1
    //   158: ldc -125
    //   160: invokestatic 76	com/appsee/bc:C	(Ljava/lang/String;)Ljava/lang/String;
    //   163: iconst_1
    //   164: anewarray 4	java/lang/Object
    //   167: dup
    //   168: iconst_0
    //   169: iload_2
    //   170: invokestatic 126	java/lang/Integer:valueOf	(I)Ljava/lang/Integer;
    //   173: aastore
    //   174: invokestatic 129	com/appsee/vd:C	(ILjava/lang/String;[Ljava/lang/Object;)V
    //   177: iload_2
    //   178: istore_1
    //   179: iload_2
    //   180: ifle -139 -> 41
    //   183: aload_0
    //   184: getfield 24	com/appsee/pd:M	Ljava/util/List;
    //   187: iload_1
    //   188: invokeinterface 62 2 0
    //   193: checkcast 35	com/appsee/bd
    //   196: astore 5
    //   198: aload_0
    //   199: getfield 24	com/appsee/pd:M	Ljava/util/List;
    //   202: aload 5
    //   204: invokeinterface 133 2 0
    //   209: pop
    //   210: aload_0
    //   211: getfield 26	com/appsee/pd:B	Ljava/util/List;
    //   214: aload 5
    //   216: invokeinterface 133 2 0
    //   221: pop
    //   222: aload 5
    //   224: invokevirtual 65	com/appsee/bd:K	()V
    //   227: aload_0
    //   228: getfield 45	com/appsee/pd:G	I
    //   231: istore_3
    //   232: iload_1
    //   233: iconst_1
    //   234: isub
    //   235: istore_2
    //   236: aload_0
    //   237: iload_3
    //   238: iconst_1
    //   239: isub
    //   240: putfield 45	com/appsee/pd:G	I
    //   243: iload_2
    //   244: istore_1
    //   245: goto -66 -> 179
    //   248: astore 5
    //   250: aload_0
    //   251: monitorexit
    //   252: aload 5
    //   254: athrow
    // Local variable table:
    //   start	length	slot	name	signature
    //   0	255	0	this	pd
    //   0	255	1	paramInt1	int
    //   0	255	2	paramInt2	int
    //   0	255	3	paramInt3	int
    //   1	136	4	i	int
    //   196	27	5	localbd	bd
    //   248	5	5	localObject	Object
    // Exception table:
    //   from	to	target	type
    //   5	21	248	finally
    //   21	41	248	finally
    //   44	115	248	finally
    //   125	131	248	finally
    //   135	145	248	finally
    //   150	177	248	finally
    //   183	232	248	finally
    //   236	243	248	finally
  }
  
  public void a()
  {
    C(this.l, this.A);
  }
}


/* Location:              D:\Android\dex2jar-2.0\classes-dex2jar.jar!\com\appsee\pd.class
 * Java compiler version: 6 (50.0)
 * JD-Core Version:       0.7.1
 */