package b.a.a.a.a.e;

import java.util.concurrent.Callable;

public abstract class l<V>
  implements Callable<V>
{
  protected abstract V b();
  
  protected abstract void c();
  
  /* Error */
  public V call()
  {
    // Byte code:
    //   0: iconst_1
    //   1: istore_1
    //   2: aload_0
    //   3: invokevirtual 22	b/a/a/a/a/e/l:b	()Ljava/lang/Object;
    //   6: astore_2
    //   7: aload_0
    //   8: invokevirtual 24	b/a/a/a/a/e/l:c	()V
    //   11: aload_2
    //   12: areturn
    //   13: astore_2
    //   14: new 18	b/a/a/a/a/e/k
    //   17: dup
    //   18: aload_2
    //   19: invokespecial 27	b/a/a/a/a/e/k:<init>	(Ljava/io/IOException;)V
    //   22: athrow
    //   23: astore_2
    //   24: aload_2
    //   25: athrow
    //   26: astore_2
    //   27: aload_0
    //   28: invokevirtual 24	b/a/a/a/a/e/l:c	()V
    //   31: aload_2
    //   32: athrow
    //   33: astore_2
    //   34: new 18	b/a/a/a/a/e/k
    //   37: dup
    //   38: aload_2
    //   39: invokespecial 27	b/a/a/a/a/e/k:<init>	(Ljava/io/IOException;)V
    //   42: athrow
    //   43: astore_3
    //   44: iload_1
    //   45: ifne -14 -> 31
    //   48: new 18	b/a/a/a/a/e/k
    //   51: dup
    //   52: aload_3
    //   53: invokespecial 27	b/a/a/a/a/e/k:<init>	(Ljava/io/IOException;)V
    //   56: athrow
    //   57: astore_2
    //   58: iconst_0
    //   59: istore_1
    //   60: goto -33 -> 27
    // Local variable table:
    //   start	length	slot	name	signature
    //   0	63	0	this	l
    //   1	59	1	i	int
    //   6	6	2	localObject1	Object
    //   13	6	2	localIOException1	java.io.IOException
    //   23	2	2	localk	k
    //   26	6	2	localObject2	Object
    //   33	6	2	localIOException2	java.io.IOException
    //   57	1	2	localObject3	Object
    //   43	10	3	localIOException3	java.io.IOException
    // Exception table:
    //   from	to	target	type
    //   7	11	13	java/io/IOException
    //   2	7	23	b/a/a/a/a/e/k
    //   24	26	26	finally
    //   34	43	26	finally
    //   2	7	33	java/io/IOException
    //   27	31	43	java/io/IOException
    //   2	7	57	finally
  }
}


/* Location:              D:\Android\dex2jar-2.0\classes-dex2jar.jar!\b\a\a\a\a\e\l.class
 * Java compiler version: 6 (50.0)
 * JD-Core Version:       0.7.1
 */